{
	"events": [
		{
			"title": "Acts",
			"time": [
				"Act 1: Week 2 on June 11",
				"Act 2: Week 7 on July 16",
				"Act 3: Week 13 on August 27"
			]
		},
		{
			"title": "Salvation's Edge",
			"time": [
				"Normal: Week 1 on June 7",
				"Master: Week 4 on June 25"
			]
		},
		{
			"title": "Iron Banner",
			"time": [
				"Week 5 on July 2",
				"TBA",
				"TBA"
			]
		},
		{ "title": "Grandmaster Nightfalls", "time": ["Week 4 on June 25"] },
		{ "title": "Solstice", "time": ["August 6, 2024 - August 26, 2024"] }
	],
	"seasonInfo": {
		"dates": "June 11, 2024 - TBA"
	}
}
